odoo/addons/mgmtsystem_quality/README.rst
odoo/addons/mgmtsystem_quality/__init__.py
odoo/addons/mgmtsystem_quality/__manifest__.py
odoo/addons/mgmtsystem_quality/data/mgmtsystem_system.xml
odoo/addons/mgmtsystem_quality/i18n/de.po
odoo/addons/mgmtsystem_quality/i18n/fr.po
odoo/addons/mgmtsystem_quality/i18n/it.po
odoo/addons/mgmtsystem_quality/i18n/mgmtsystem_quality.pot
odoo/addons/mgmtsystem_quality/i18n/nb.po
odoo/addons/mgmtsystem_quality/i18n/pt_BR.po
odoo/addons/mgmtsystem_quality/i18n/sv.po
odoo/addons/mgmtsystem_quality/i18n/vi.po
odoo/addons/mgmtsystem_quality/readme/CONFIGURE.rst
odoo/addons/mgmtsystem_quality/readme/CONTRIBUTORS.rst
odoo/addons/mgmtsystem_quality/readme/DESCRIPTION.rst
odoo/addons/mgmtsystem_quality/readme/ROADMAP.rst
odoo/addons/mgmtsystem_quality/readme/USAGE.rst
odoo/addons/mgmtsystem_quality/static/description/icon.png
odoo/addons/mgmtsystem_quality/static/description/index.html
odoo14_addon_mgmtsystem_quality-14.0.1.0.1.dev5.dist-info/METADATA
odoo14_addon_mgmtsystem_quality-14.0.1.0.1.dev5.dist-info/WHEEL
odoo14_addon_mgmtsystem_quality-14.0.1.0.1.dev5.dist-info/top_level.txt
odoo14_addon_mgmtsystem_quality-14.0.1.0.1.dev5.dist-info/RECORD
