Metadata-Version: 2.1
Name: odoo14-addon-mgmtsystem-quality
Version: 14.0.1.0.1.dev5
Summary: Manage your quality management system
Home-page: https://github.com/OCA/management-system
Author: Savoir-faire Linux, Odoo Community Association (OCA)
Author-email: support@odoo-community.org
License: AGPL-3
Platform: UNKNOWN
Classifier: Programming Language :: Python
Classifier: Framework :: Odoo
Classifier: Framework :: Odoo :: 14.0
Classifier: License :: OSI Approved :: GNU Affero General Public License v3
Classifier: Development Status :: 5 - Production/Stable
Requires-Python: >=3.6
Requires-Dist: odoo14-addon-document-page-quality-manual
Requires-Dist: odoo14-addon-mgmtsystem-audit
Requires-Dist: odoo14-addon-mgmtsystem-manual
Requires-Dist: odoo14-addon-mgmtsystem-review
Requires-Dist: odoo <14.1dev,>=14.0a
